{
  "id": "3555182",
  "name": "电商",
  "font_family": "iconfont",
  "css_prefix_text": "icon-",
  "description": "",
  "glyphs": [
    {
      "icon_id": "4765896",
      "name": "eye",
      "font_class": "eye",
      "unicode": "e78f",
      "unicode_decimal": 59279
    },
    {
      "icon_id": "6994848",
      "name": "eye",
      "font_class": "eye1",
      "unicode": "e613",
      "unicode_decimal": 58899
    },
    {
      "icon_id": "1418250",
      "name": "loading",
      "font_class": "loading1",
      "unicode": "e61c",
      "unicode_decimal": 58908
    },
    {
      "icon_id": "1305488",
      "name": "loading",
      "font_class": "loading",
      "unicode": "e644",
      "unicode_decimal": 58948
    },
    {
      "icon_id": "1274418",
      "name": "icon_QQ",
      "font_class": "QQ",
      "unicode": "e65e",
      "unicode_decimal": 58974
    },
    {
      "icon_id": "2674927",
      "name": "箭头 上",
      "font_class": "jiantoushang",
      "unicode": "e62d",
      "unicode_decimal": 58925
    },
    {
      "icon_id": "2674929",
      "name": "箭头 下",
      "font_class": "jiantouxia",
      "unicode": "e62e",
      "unicode_decimal": 58926
    },
    {
      "icon_id": "1718353",
      "name": "下箭头",
      "font_class": "xiajiantou",
      "unicode": "e606",
      "unicode_decimal": 58886
    },
    {
      "icon_id": "1718351",
      "name": "上箭头",
      "font_class": "shangjiantou",
      "unicode": "e604",
      "unicode_decimal": 58884
    },
    {
      "icon_id": "4175512",
      "name": "上箭头",
      "font_class": "shangjiantou1",
      "unicode": "eb6d",
      "unicode_decimal": 60269
    },
    {
      "icon_id": "8574949",
      "name": "微信支付",
      "font_class": "weixinzhifu",
      "unicode": "e607",
      "unicode_decimal": 58887
    },
    {
      "icon_id": "15933089",
      "name": "支付宝",
      "font_class": "zhifubao",
      "unicode": "e608",
      "unicode_decimal": 58888
    },
    {
      "icon_id": "696569",
      "name": "安卓logo",
      "font_class": "anzhuologo",
      "unicode": "e679",
      "unicode_decimal": 59001
    },
    {
      "icon_id": "396307",
      "name": "sey-talk-b",
      "font_class": "sey-talk-b",
      "unicode": "e667",
      "unicode_decimal": 58983
    },
    {
      "icon_id": "17397806",
      "name": "talk",
      "font_class": "talk",
      "unicode": "e7b1",
      "unicode_decimal": 59313
    },
    {
      "icon_id": "201525",
      "name": "礼物 活动",
      "font_class": "liwuhuodong",
      "unicode": "e602",
      "unicode_decimal": 58882
    },
    {
      "icon_id": "201579",
      "name": "3.1定位",
      "font_class": "31dingwei",
      "unicode": "e603",
      "unicode_decimal": 58883
    },
    {
      "icon_id": "1093910",
      "name": "15天包退",
      "font_class": "15tianbaotui01",
      "unicode": "e688",
      "unicode_decimal": 59016
    },
    {
      "icon_id": "1307682",
      "name": "7天包退",
      "font_class": "7tianbaotui",
      "unicode": "e6cc",
      "unicode_decimal": 59084
    },
    {
      "icon_id": "11813323",
      "name": "修理",
      "font_class": "xiuli",
      "unicode": "e624",
      "unicode_decimal": 58916
    },
    {
      "icon_id": "629357",
      "name": "搜索",
      "font_class": "sousuo",
      "unicode": "e651",
      "unicode_decimal": 58961
    },
    {
      "icon_id": "5127426",
      "name": "mobile",
      "font_class": "mobile",
      "unicode": "e7d6",
      "unicode_decimal": 59350
    },
    {
      "icon_id": "145491",
      "name": "箭头",
      "font_class": "jiantou",
      "unicode": "e662",
      "unicode_decimal": 58978
    },
    {
      "icon_id": "6880726",
      "name": "购物车",
      "font_class": "gouwuche",
      "unicode": "e61e",
      "unicode_decimal": 58910
    },
    {
      "icon_id": "30747882",
      "name": "云物流",
      "font_class": "ambitus02",
      "unicode": "e600",
      "unicode_decimal": 58880
    },
    {
      "icon_id": "30747883",
      "name": "云营销",
      "font_class": "ambitus03",
      "unicode": "e601",
      "unicode_decimal": 58881
    }
  ]
}
